LICENCE.txt
README.md
setup.py
django_project_center.egg-info/PKG-INFO
django_project_center.egg-info/SOURCES.txt
django_project_center.egg-info/dependency_links.txt
django_project_center.egg-info/not-zip-safe
django_project_center.egg-info/top_level.txt
project_center/__init__.py
project_center/admin.py
project_center/apps.py
project_center/models.py
project_center/storage_backends.py
project_center/tests.py
project_center/utils.py
project_center/views.py
project_center/management/__init__.py
project_center/management/commands/__init__.py
project_center/management/commands/check_aws_access.py
project_center/management/commands/send_project_alert_email.py
project_center/migrations/0001_initial.py
project_center/migrations/0002_user_email_notify.py
project_center/migrations/0003_projectactivity_notes.py
project_center/migrations/0004_projectcategory_display.py
project_center/migrations/0005_projectstatus_display.py
project_center/migrations/0006_projectstage_display.py
project_center/migrations/0007_alter_company_options_alter_user_options_and_more.py
project_center/migrations/0008_activity_projectactivity_reply_alter_project_users_and_more.py
project_center/migrations/0009_projectactivity_reply_file_and_more.py
project_center/migrations/0010_delete_activity_project_last_activity_date_and_more.py
project_center/migrations/0011_project_last_activity_name.py
project_center/migrations/0012_alter_projectactivity_file.py
project_center/migrations/0013_projectactivity_pin.py
project_center/migrations/__init__.py
project_center/signals/__init__.py
project_center/signals/handlers.py
project_center/templates/__init__.py
project_center/templates/email/__init__.py