Metadata-Version: 2.1
Name: django-project-center
Version: 1.3
Summary: Project Management Module for Django
Home-page: https://github.com/pdbethke/django-project-center
Author: siteshell.net
Author-email: pdbethke@siteshell.net
License: LICENSE.txt
Platform: OS Independent
License-File: LICENCE.txt
